{"transcript":"dʒis.ku.ˈtʃiʁ","exists":true,"definitions":["Debater um assunto detalhadamente.","Trocar argumentos de forma calorosa ou conflituosa.","Analisar ou examinar algo sob diferentes pontos de vista."],"examples":["Eles precisam discutir o projeto.","Não vale a pena discutir por isso.","Vamos discutir as opções amanhã."],"lemma":"discutir","lemmaPos":"verb","synonyms":["debater","argumentar","questionar","altercar"],"number":"singular","pastTenses":"discuti, discutira, tinha discutido","tense":"present","source":"discutir"}