{"transcript":"esˈtudu","exists":true,"definitions":["Ato ou efeito de estudar; aplicação da inteligência para aprender ou conhecer algo.","Pesquisa ou análise aprofundada sobre um determinado assunto.","Obra ou trabalho resultante de uma investigação ou pesquisa.","Local onde se estuda ou trabalha, como um escritório ou ateliê."],"examples":["O estudo da matemática é fascinante.","Ele dedicou anos ao estudo da física quântica.","Publicou um estudo sobre o aquecimento global.","Seu estudo está sempre organizado."],"lemma":"estudar","lemmaPos":"verb","synonyms":["aprendizagem","análise","pesquisa","investigação","escritório"],"number":"singular","pluralForm":"os estudos","gender":"masculine","source":"estudo"}