{"transcript":"ka.ˈmi.zɐ dʒi ˈvẽ.nus","exists":true,"definitions":["Invólucro de látex ou outro material usado no pênis durante o ato sexual como contraceptivo ou proteção contra doenças.","Designação popular para o preservativo ou camisinha."],"examples":["O uso da camisa-de-vênus previne ISTs.","Ele comprou uma caixa de camisa-de-vênus na farmácia."],"lemma":"camisa-de-vênus","lemmaPos":"noun","synonyms":["preservativo","camisinha","vênus","condom"],"number":"singular","pluralForm":"as camisas-de-vênus","gender":"feminine","source":"camisa-de-vênus"}