{"transcript":"plaˈkaʁ","exists":true,"definitions":["Quadro ou painel onde se registram os pontos ou resultados de uma competição esportiva.","O resultado numérico de uma partida ou disputa."],"examples":["O placar do jogo foi dois a zero.","Olhe para o placar para ver quanto tempo falta.","Eles abriram o placar no primeiro tempo."],"lemma":"placar","lemmaPos":"noun","synonyms":["marcador","escore","tabela","resultado"],"number":"singular","pluralForm":"os placares","gender":"masculine","source":"placar"}