{"source":"Eu lavo os pisos no apartamento todos os dias","definitions":["Ato de limpar ou purificar algo com água ou outro líquido, geralmente esfregando.","Ato de remover sujeira, manchas ou impurezas de uma superfície ou objeto.","Ato de banhar-se ou higienizar-se."],"examples":["Lavo minhas mãos antes de comer.","Lavo o carro todo sábado.","Lavo a louça depois do jantar."],"lemma":"lavar","lemmaPos":"verb","synonyms":["limpar","higienizar","purificar","esfregar","banhar"],"number":"singular","gender":"other","transcript":""}