{"transcript":"keˈɾemuʃ","exists":true,"definitions":["Primeira pessoa do plural do presente do indicativo do verbo querer.","Ter desejo ou vontade de algo.","Almejar, desejar, cobiçar.","Precisar, necessitar."],"examples":["Nós queremos paz.","Queremos ir ao cinema hoje.","Se queremos, podemos.","Queremos que você venha."],"lemma":"querer","lemmaPos":"verb","synonyms":["desejamos","almejamos","precisamos","necessitamos"],"number":"plural","pastTenses":"nós quisemos, nós tínhamos querido","tense":"present","source":"queremos"}