{"transcript":"eˈmẽ.tɐ","exists":true,"definitions":["Resumo ou síntese de uma decisão judicial ou de um texto legal.","Lista de pratos servidos em uma refeição; cardápio.","Anotação ou lembrete de algo a ser feito."],"examples":["A ementa do acórdão foi publicada.","O restaurante mudou a ementa hoje.","Escrevi uma ementa para não esquecer o compromisso."],"lemma":"ementa","lemmaPos":"noun","synonyms":["sumário","resumo","cardápio","anotação"],"number":"singular","pluralForm":"as ementas","gender":"feminine","source":"ementa"}